Workbook

Sheet Read Me
A1: Soblabs BOM template — proposed v1
A2: Internal workbook: contains supplier costs and profit. Do not send to customers.
A3: Use Project for project details; use BOM Items for all rooms and systems.
A4: Blue headings are inputs. Purple headings are calculated fields.
A5: One row per item. Keep Item ID stable across revisions; assign a unique ID to each new row.
A6: Scope: Selected contributes to totals; Alternative and Excluded do not.
A7: Unit describes quantity: ea, hour, metre, lot, etc. Do not infer labour units.
A8: Cost Currency: CAD or USD. FX to Project Currency = project currency units per 1 cost currency unit.
A9: Example: USD cost to CAD project at 1 USD = 1.35 CAD uses FX 1.35; same currency uses 1.
A10: Enter Markup as an Excel percentage (25%). This template uses markup, not target margin.
A11: Tax Rate is project-specific; taxable status is per item. No default jurisdiction is assumed.
A12: Supplier SKU and manufacturer part number are text to preserve leading zeros.
... A17: App imports should preview changes and retain the source workbook. No SharePoint sync is connected yet.

Sheet Project
A1: Field | B1: Value
A2: Project ID
A3: Project Name
A4: Customer
A5: Site / Address
A6: Revision | B6: 1
A7: Prepared By
A8: Issue Date
A9: Valid Until
A10: Project Currency | B10: CAD
A11: Tax Rate
A12: Payment Terms
A13: Notes / Exclusions

Sheet BOM Items
A1: Item ID | B1: Area / System | C1: Scope | D1: Category | E1: Manufacturer | F1: Manufacturer Part No | G1: Description | H1: Supplier | I1: Supplier SKU | J1: Quantity | K1: Unit | L1: Unit Cost | M1: Cost Currency | N1: FX to Project Currency | O1: Markup % | P1: Taxable | Q1: Lead Time Days | R1: Notes | S1: Readiness | T1: Extended Cost | U1: Unit Sell Price | V1: Extended Sell Price | W1: Gross Profit | X1: Margin % | Y1: Tax
S2: =IF(A2="","",IF(OR(C2="",G2="",J2="",K2="",L2="",M2="",N2="",O2="",P2="",Project!$B$10="",Project!$B$11=""),"Incomplete","Ready")) | T2: =IF(S2<>"Ready","",ROUND(J2*L2*N2,2)) | U2: =IF(S2<>"Ready","",ROUND(L2*N2*(1+O2),2)) | V2: =IF(S2<>"Ready","",ROUND(J2*U2,2)) | W2: =IF(S2<>"Ready","",V2-T2) | X2: =IF(S2<>"Ready","",IF(V2=0,0,W2/V2)) | Y2: =IF(S2<>"Ready","",IF(P2="Yes",ROUND(V2*Project!$B$11,2),0))
S3: =IF(A3="","",IF(OR(C3="",G3="",J3="",K3="",L3="",M3="",N3="",O3="",P3="",Project!$B$10="",Project!$B$11=""),"Incomplete","Ready")) | T3: =IF(S3<>"Ready","",ROUND(J3*L3*N3,2)) | U3: =IF(S3<>"Ready","",ROUND(L3*N3*(1+O3),2)) | V3: =IF(S3<>"Ready","",ROUND(J3*U3,2)) | W3: =IF(S3<>"Ready","",V3-T3) | X3: =IF(S3<>"Ready","",IF(V3=0,0,W3/V3)) | Y3: =IF(S3<>"Ready","",IF(P3="Yes",ROUND(V3*Project!$B$11,2),0))
S4: =IF(A4="","",IF(OR(C4="",G4="",J4="",K4="",L4="",M4="",N4="",O4="",P4="",Project!$B$10="",Project!$B$11=""),"Incomplete","Ready")) | T4: =IF(S4<>"Ready","",ROUND(J4*L4*N4,2)) | U4: =IF(S4<>"Ready","",ROUND(L4*N4*(1+O4),2)) | V4: =IF(S4<>"Ready","",ROUND(J4*U4,2)) | W4: =IF(S4<>"Ready","",V4-T4) | X4: =IF(S4<>"Ready","",IF(V4=0,0,W4/V4)) | Y4: =IF(S4<>"Ready","",IF(P4="Yes",ROUND(V4*Project!$B$11,2),0))
S5: =IF(A5="","",IF(OR(C5="",G5="",J5="",K5="",L5="",M5="",N5="",O5="",P5="",Project!$B$10="",Project!$B$11=""),"Incomplete","Ready")) | T5: =IF(S5<>"Ready","",ROUND(J5*L5*N5,2)) | U5: =IF(S5<>"Ready","",ROUND(L5*N5*(1+O5),2)) | V5: =IF(S5<>"Ready","",ROUND(J5*U5,2)) | W5: =IF(S5<>"Ready","",V5-T5) | X5: =IF(S5<>"Ready","",IF(V5=0,0,W5/V5)) | Y5: =IF(S5<>"Ready","",IF(P5="Yes",ROUND(V5*Project!$B$11,2),0))
S6: =IF(A6="","",IF(OR(C6="",G6="",J6="",K6="",L6="",M6="",N6="",O6="",P6="",Project!$B$10="",Project!$B$11=""),"Incomplete","Ready")) | T6: =IF(S6<>"Ready","",ROUND(J6*L6*N6,2)) | U6: =IF(S6<>"Ready","",ROUND(L6*N6*(1+O6),2)) | V6: =IF(S6<>"Ready","",ROUND(J6*U6,2)) | W6: =IF(S6<>"Ready","",V6-T6) | X6: =IF(S6<>"Ready","",IF(V6=0,0,W6/V6)) | Y6: =IF(S6<>"Ready","",IF(P6="Yes",ROUND(V6*Project!$B$11,2),0))
S7: =IF(A7="","",IF(OR(C7="",G7="",J7="",K7="",L7="",M7="",N7="",O7="",P7="",Project!$B$10="",Project!$B$11=""),"Incomplete","Ready")) | T7: =IF(S7<>"Ready","",ROUND(J7*L7*N7,2)) | U7: =IF(S7<>"Ready","",ROUND(L7*N7*(1+O7),2)) | V7: =IF(S7<>"Ready","",ROUND(J7*U7,2)) | W7: =IF(S7<>"Ready","",V7-T7) | X7: =IF(S7<>"Ready","",IF(V7=0,0,W7/V7)) | Y7: =IF(S7<>"Ready","",IF(P7="Yes",ROUND(V7*Project!$B$11,2),0))
S8: =IF(A8="","",IF(OR(C8="",G8="",J8="",K8="",L8="",M8="",N8="",O8="",P8="",Project!$B$10="",Project!$B$11=""),"Incomplete","Ready")) | T8: =IF(S8<>"Ready","",ROUND(J8*L8*N8,2)) | U8: =IF(S8<>"Ready","",ROUND(L8*N8*(1+O8),2)) | V8: =IF(S8<>"Ready","",ROUND(J8*U8,2)) | W8: =IF(S8<>"Ready","",V8-T8) | X8: =IF(S8<>"Ready","",IF(V8=0,0,W8/V8)) | Y8: =IF(S8<>"Ready","",IF(P8="Yes",ROUND(V8*Project!$B$11,2),0))
S9: =IF(A9="","",IF(OR(C9="",G9="",J9="",K9="",L9="",M9="",N9="",O9="",P9="",Project!$B$10="",Project!$B$11=""),"Incomplete","Ready")) | T9: =IF(S9<>"Ready","",ROUND(J9*L9*N9,2)) | U9: =IF(S9<>"Ready","",ROUND(L9*N9*(1+O9),2)) | V9: =IF(S9<>"Ready","",ROUND(J9*U9,2)) | W9: =IF(S9<>"Ready","",V9-T9) | X9: =IF(S9<>"Ready","",IF(V9=0,0,W9/V9)) | Y9: =IF(S9<>"Ready","",IF(P9="Yes",ROUND(V9*Project!$B$11,2),0))
S10: =IF(A10="","",IF(OR(C10="",G10="",J10="",K10="",L10="",M10="",N10="",O10="",P10="",Project!$B$10="",Project!$B$11=""),"Incomplete","Ready")) | T10: =IF(S10<>"Ready","",ROUND(J10*L10*N10,2)) | U10: =IF(S10<>"Ready","",ROUND(L10*N10*(1+O10),2)) | V10: =IF(S10<>"Ready","",ROUND(J10*U10,2)) | W10: =IF(S10<>"Ready","",V10-T10) | X10: =IF(S10<>"Ready","",IF(V10=0,0,W10/V10)) | Y10: =IF(S10<>"Ready","",IF(P10="Yes",ROUND(V10*Project!$B$11,2),0))
S11: =IF(A11="","",IF(OR(C11="",G11="",J11="",K11="",L11="",M11="",N11="",O11="",P11="",Project!$B$10="",Project!$B$11=""),"Incomplete","Ready")) | T11: =IF(S11<>"Ready","",ROUND(J11*L11*N11,2)) | U11: =IF(S11<>"Ready","",ROUND(L11*N11*(1+O11),2)) | V11: =IF(S11<>"Ready","",ROUND(J11*U11,2)) | W11: =IF(S11<>"Ready","",V11-T11) | X11: =IF(S11<>"Ready","",IF(V11=0,0,W11/V11)) | Y11: =IF(S11<>"Ready","",IF(P11="Yes",ROUND(V11*Project!$B$11,2),0))
S12: =IF(A12="","",IF(OR(C12="",G12="",J12="",K12="",L12="",M12="",N12="",O12="",P12="",Project!$B$10="",Project!$B$11=""),"Incomplete","Ready")) | T12: =IF(S12<>"Ready","",ROUND(J12*L12*N12,2)) | U12: =IF(S12<>"Ready","",ROUND(L12*N12*(1+O12),2)) | V12: =IF(S12<>"Ready","",ROUND(J12*U12,2)) | W12: =IF(S12<>"Ready","",V12-T12) | X12: =IF(S12<>"Ready","",IF(V12=0,0,W12/V12)) | Y12: =IF(S12<>"Ready","",IF(P12="Yes",ROUND(V12*Project!$B$11,2),0))
S13: =IF(A13="","",IF(OR(C13="",G13="",J13="",K13="",L13="",M13="",N13="",O13="",P13="",Project!$B$10="",Project!$B$11=""),"Incomplete","Ready")) | T13: =IF(S13<>"Ready","",ROUND(J13*L13*N13,2)) | U13: =IF(S13<>"Ready","",ROUND(L13*N13*(1+O13),2)) | V13: =IF(S13<>"Ready","",ROUND(J13*U13,2)) | W13: =IF(S13<>"Ready","",V13-T13) | X13: =IF(S13<>"Ready","",IF(V13=0,0,W13/V13)) | Y13: =IF(S13<>"Ready","",IF(P13="Yes",ROUND(V13*Project!$B$11,2),0))
... S101: =IF(A101="","",IF(OR(C101="",G101="",J101="",K101="",L101="",M101="",N101="",O101="",P101="",Project!$B$10="",Project!$B$11=""),"Incomplete","Ready")) | T101: =IF(S101<>"Ready","",ROUND(J101*L101*N101,2)) | U101: =IF(S101<>"Ready","",ROUND(L101*N101*(1+O101),2)) | V101: =IF(S101<>"Ready","",ROUND(J101*U101,2)) | W101: =IF(S101<>"Ready","",V101-T101) | X101: =IF(S101<>"Ready","",IF(V101=0,0,W101/V101)) | Y101: =IF(S101<>"Ready","",IF(P101="Yes",ROUND(V101*Project!$B$11,2),0))

Sheet Summary
A1: Metric | B1: Value
A2: Project Currency | B2: =Project!B10
A3: Selected Incomplete Items | B3: =COUNTIFS('BOM Items'!C2:C101,"Selected",'BOM Items'!S2:S101,"Incomplete")
A4: Selected Cost | B4: =SUMIF('BOM Items'!C2:C101,"Selected",'BOM Items'!T2:T101)
A5: Selected Selling Subtotal | B5: =SUMIF('BOM Items'!C2:C101,"Selected",'BOM Items'!V2:V101)
A6: Gross Profit | B6: =B5-B4
A7: Gross Margin | B7: =IF(B5=0,0,B6/B5)
A8: Tax | B8: =SUMIF('BOM Items'!C2:C101,"Selected",'BOM Items'!Y2:Y101)
A9: Total Including Tax | B9: =B5+B8
A10: Status | B10: =IF(B3>0,"Incomplete — totals omit incomplete lines","Check scope and inputs before approval")
